contextplot/__init__.py
contextplot-0.0.4.dist-info/LICENSE
contextplot-0.0.4.dist-info/METADATA
contextplot-0.0.4.dist-info/WHEEL
contextplot-0.0.4.dist-info/top_level.txt
contextplot-0.0.4.dist-info/RECORD
